[{"Id":1,"Author":"Muker","Name":"","Title":"NOVA 鱼油","Content":" <p>\n                  Experience the future of wearable technology with our Premium\n                  Smart Watch. Featuring a stunning AMOLED display,\n                  comprehensive health tracking, and seamless connectivity, this\n                  watch is designed to elevate your daily life.\n                </p>\n                <ul class=\"features-list\">\n                  <li>AMOLED touch display</li>\n                  <li>Heart rate & SpO2 monitoring</li>\n                  <li>50m water resistance</li>\n                  <li>7-day battery life</li>\n                  <li>Multiple sport modes</li>\n                </ul>\n\n                <p>\n                  Experience the future of wearable technology with our Premium\n                  Smart Watch. Featuring a stunning AMOLED display,\n                  comprehensive health tracking, and seamless connectivity, this\n                  watch is designed to elevate your daily life.\n                </p>\n                <ul class=\"features-list\">\n                  <li>AMOLED touch display</li>\n                  <li>Heart rate & SpO2 monitoring</li>\n                  <li>50m water resistance</li>\n                  <li>7-day battery life</li>\n                  <li>Multiple sport modes</li>\n                </ul>\n                <p>\n                  Experience the future of wearable technology with our Premium\n                  Smart Watch. Featuring a stunning AMOLED display,\n                  comprehensive health tracking, and seamless connectivity, this\n                  watch is designed to elevate your daily life.\n                </p>\n                <ul class=\"features-list\">\n                  <li>AMOLED touch display</li>\n                  <li>Heart rate & SpO2 monitoring</li>\n                  <li>50m water resistance</li>\n                  <li>7-day battery life</li>\n                  <li>Multiple sport modes</li>\n                </ul>\n                <p>\n                  Experience the future of wearable technology with our Premium\n                  Smart Watch. Featuring a stunning AMOLED display,\n                  comprehensive health tracking, and seamless connectivity, this\n                  watch is designed to elevate your daily life.\n                </p>\n                <ul class=\"features-list\">\n                  <li>AMOLED touch display</li>\n                  <li>Heart rate & SpO2 monitoring</li>\n                  <li>50m water resistance</li>\n                  <li>7-day battery life</li>\n                  <li>Multiple sport modes</li>\n                </ul>","ModelPath":"assets\\models\\exhibits\\bottle.glb","Url":"https://orihealth.my","CSPhone":"0182064248","IsRedirect":2,"MLocation":"p1.r1.019","OffsetZ":0.0,"OffsetY":-0.4,"OffsetX":0.0,"X":9999,"Y":9999,"Z":9999,"show_boards":true}]